{
  "list" : [
    {
      "version" : "current",
      "path" : "https://build.fhir.org/ig/kip-infrastructure/implementation-guide/",
      "status" : "ci-build",
      "sequence" : "ci-build"
    },
    {
      "version" : "2.9.3",
      "path" : "https://kip.rkkp.dk/fhir/2.9.3",
      "status" : "release",
      "sequence" : "Releases",
      "fhirversion" : "4.0.1",
      "date" : "2025-03-17",
      "current" : true,
      "desc" : "KIP Infrastructure version 2.9.3",
      "descmd" : "* See detailed changes in [the changelog](https://kip.sundk.dk/fhir/changelog.html#replace-me)"
    },
    {
      "version" : "2.9.1",
      "path" : "https://kip.rkkp.dk/fhir/2.9.1",
      "status" : "release",
      "sequence" : "Releases",
      "fhirversion" : "4.0.1",
      "date" : "2025-03-17",
      "desc" : "KIP Infrastructure version 2.9.1",
      "descmd" : "* See detailed changes in [the changelog](https://kip.sundk.dk/fhir/changelog.html#replace-me)"
    },
    {
      "version" : "2.9.0",
      "path" : "https://kip.rkkp.dk/fhir/2.9.0",
      "status" : "release",
      "sequence" : "Releases",
      "fhirversion" : "4.0.1",
      "date" : "2025-03-14",
      "desc" : "KIP Infrastructure version 2.9.0",
      "descmd" : "* See detailed changes in [the changelog](https://kip.sundk.dk/fhir/changelog.html#replace-me)"
    },
    {
      "version" : "0.2.1",
      "path" : "https://kip.rkkp.dk/fhir/0.2.1",
      "status" : "release",
      "sequence" : "Releases",
      "fhirversion" : "4.0.1",
      "date" : "2025-03-14",
      "desc" : "KIP Infrastructure version 0.2.1",
      "descmd" : "* See detailed changes in [the changelog](https://kip.sundk.dk/fhir/changelog.html#replace-me)"
    },
    {
      "version" : "0.1.8",
      "path" : "https://kip.rkkp.dk/fhir/0.1.8",
      "status" : "release",
      "sequence" : "Releases",
      "fhirversion" : "4.0.1",
      "date" : "2025-03-13",
      "desc" : "KIP Infrastructure version 0.1.8",
      "descmd" : "* See detailed changes in [the changelog](https://kip.sundk.dk/fhir/changelog.html#replace-me)"
    }
  ],
  "package-id" : "dk.kip.rkkp.fhir.ig.core",
  "canonical" : "https://kip.rkkp.dk/fhir",
  "title" : "KIP Infrastructure",
  "category" : "Core",
  "introduction" : "A FHIR Implementation Guide for KIP Infrastructure"
}
